{"__ssr_module_mapping__":{"2092":{"":{"id":"6862","name":"","chunks":["272:webpack-37ca05abd9f556e4","17:17-f2d707dd60cbbe95","744:main-app-e2b4ac6faab5ed41"],"async":false},"*":{"id":"6862","name":"*","chunks":["272:webpack-37ca05abd9f556e4","17:17-f2d707dd60cbbe95","744:main-app-e2b4ac6faab5ed41"],"async":false},"default":{"id":"6862","name":"default","chunks":["272:webpack-37ca05abd9f556e4","17:17-f2d707dd60cbbe95","744:main-app-e2b4ac6faab5ed41"],"async":false}},"7043":{"":{"id":"2030","name":"","chunks":["272:webpack-37ca05abd9f556e4","17:17-f2d707dd60cbbe95","744:main-app-e2b4ac6faab5ed41"],"async":false},"*":{"id":"2030","name":"*","chunks":["272:webpack-37ca05abd9f556e4","17:17-f2d707dd60cbbe95","744:main-app-e2b4ac6faab5ed41"],"async":false},"default":{"id":"2030","name":"default","chunks":["272:webpack-37ca05abd9f556e4","17:17-f2d707dd60cbbe95","744:main-app-e2b4ac6faab5ed41"],"async":false}},"7954":{"":{"id":"9446","name":"","chunks":["272:webpack-37ca05abd9f556e4","17:17-f2d707dd60cbbe95","744:main-app-e2b4ac6faab5ed41"],"async":false},"*":{"id":"9446","name":"*","chunks":["272:webpack-37ca05abd9f556e4","17:17-f2d707dd60cbbe95","744:main-app-e2b4ac6faab5ed41"],"async":false},"default":{"id":"9446","name":"default","chunks":["272:webpack-37ca05abd9f556e4","17:17-f2d707dd60cbbe95","744:main-app-e2b4ac6faab5ed41"],"async":false}},"9875":{"":{"id":"3258","name":"","chunks":["272:webpack-37ca05abd9f556e4","17:17-f2d707dd60cbbe95","744:main-app-e2b4ac6faab5ed41"],"async":false},"*":{"id":"3258","name":"*","chunks":["272:webpack-37ca05abd9f556e4","17:17-f2d707dd60cbbe95","744:main-app-e2b4ac6faab5ed41"],"async":false},"default":{"id":"3258","name":"default","chunks":["272:webpack-37ca05abd9f556e4","17:17-f2d707dd60cbbe95","744:main-app-e2b4ac6faab5ed41"],"async":false}}},"__edge_ssr_module_mapping__":{},"__entry_css_files__":{"/Users/byronwade/Desktop/emailmework.com/app/layout":["static/css/2b2c5c4a8fea1859.css"]},"/Users/byronwade/Desktop/emailmework.com/node_modules/next/dist/client/components/app-router.js":{"":{"id":"7954","name":"","chunks":["272:webpack-37ca05abd9f556e4","17:17-f2d707dd60cbbe95","744:main-app-e2b4ac6faab5ed41"],"async":false},"*":{"id":"7954","name":"*","chunks":["272:webpack-37ca05abd9f556e4","17:17-f2d707dd60cbbe95","744:main-app-e2b4ac6faab5ed41"],"async":false},"default":{"id":"7954","name":"default","chunks":["272:webpack-37ca05abd9f556e4","17:17-f2d707dd60cbbe95","744:main-app-e2b4ac6faab5ed41"],"async":false}},"/Users/byronwade/Desktop/emailmework.com/node_modules/next/dist/esm/client/components/app-router.js":{"":{"id":"7954","name":"","chunks":["272:webpack-37ca05abd9f556e4","17:17-f2d707dd60cbbe95","744:main-app-e2b4ac6faab5ed41"],"async":false},"*":{"id":"7954","name":"*","chunks":["272:webpack-37ca05abd9f556e4","17:17-f2d707dd60cbbe95","744:main-app-e2b4ac6faab5ed41"],"async":false},"default":{"id":"7954","name":"default","chunks":["272:webpack-37ca05abd9f556e4","17:17-f2d707dd60cbbe95","744:main-app-e2b4ac6faab5ed41"],"async":false}},"/Users/byronwade/Desktop/emailmework.com/node_modules/next/dist/client/components/error-boundary.js":{"":{"id":"7043","name":"","chunks":["272:webpack-37ca05abd9f556e4","17:17-f2d707dd60cbbe95","744:main-app-e2b4ac6faab5ed41"],"async":false},"*":{"id":"7043","name":"*","chunks":["272:webpack-37ca05abd9f556e4","17:17-f2d707dd60cbbe95","744:main-app-e2b4ac6faab5ed41"],"async":false},"default":{"id":"7043","name":"default","chunks":["272:webpack-37ca05abd9f556e4","17:17-f2d707dd60cbbe95","744:main-app-e2b4ac6faab5ed41"],"async":false}},"/Users/byronwade/Desktop/emailmework.com/node_modules/next/dist/esm/client/components/error-boundary.js":{"":{"id":"7043","name":"","chunks":["272:webpack-37ca05abd9f556e4","17:17-f2d707dd60cbbe95","744:main-app-e2b4ac6faab5ed41"],"async":false},"*":{"id":"7043","name":"*","chunks":["272:webpack-37ca05abd9f556e4","17:17-f2d707dd60cbbe95","744:main-app-e2b4ac6faab5ed41"],"async":false},"default":{"id":"7043","name":"default","chunks":["272:webpack-37ca05abd9f556e4","17:17-f2d707dd60cbbe95","744:main-app-e2b4ac6faab5ed41"],"async":false}},"/Users/byronwade/Desktop/emailmework.com/node_modules/next/dist/client/components/layout-router.js":{"":{"id":"9875","name":"","chunks":["272:webpack-37ca05abd9f556e4","17:17-f2d707dd60cbbe95","744:main-app-e2b4ac6faab5ed41"],"async":false},"*":{"id":"9875","name":"*","chunks":["272:webpack-37ca05abd9f556e4","17:17-f2d707dd60cbbe95","744:main-app-e2b4ac6faab5ed41"],"async":false},"default":{"id":"9875","name":"default","chunks":["272:webpack-37ca05abd9f556e4","17:17-f2d707dd60cbbe95","744:main-app-e2b4ac6faab5ed41"],"async":false}},"/Users/byronwade/Desktop/emailmework.com/node_modules/next/dist/esm/client/components/layout-router.js":{"":{"id":"9875","name":"","chunks":["272:webpack-37ca05abd9f556e4","17:17-f2d707dd60cbbe95","744:main-app-e2b4ac6faab5ed41"],"async":false},"*":{"id":"9875","name":"*","chunks":["272:webpack-37ca05abd9f556e4","17:17-f2d707dd60cbbe95","744:main-app-e2b4ac6faab5ed41"],"async":false},"default":{"id":"9875","name":"default","chunks":["272:webpack-37ca05abd9f556e4","17:17-f2d707dd60cbbe95","744:main-app-e2b4ac6faab5ed41"],"async":false}},"/Users/byronwade/Desktop/emailmework.com/node_modules/next/dist/client/components/render-from-template-context.js":{"":{"id":"2092","name":"","chunks":["272:webpack-37ca05abd9f556e4","17:17-f2d707dd60cbbe95","744:main-app-e2b4ac6faab5ed41"],"async":false},"*":{"id":"2092","name":"*","chunks":["272:webpack-37ca05abd9f556e4","17:17-f2d707dd60cbbe95","744:main-app-e2b4ac6faab5ed41"],"async":false},"default":{"id":"2092","name":"default","chunks":["272:webpack-37ca05abd9f556e4","17:17-f2d707dd60cbbe95","744:main-app-e2b4ac6faab5ed41"],"async":false}},"/Users/byronwade/Desktop/emailmework.com/node_modules/next/dist/esm/client/components/render-from-template-context.js":{"":{"id":"2092","name":"","chunks":["272:webpack-37ca05abd9f556e4","17:17-f2d707dd60cbbe95","744:main-app-e2b4ac6faab5ed41"],"async":false},"*":{"id":"2092","name":"*","chunks":["272:webpack-37ca05abd9f556e4","17:17-f2d707dd60cbbe95","744:main-app-e2b4ac6faab5ed41"],"async":false},"default":{"id":"2092","name":"default","chunks":["272:webpack-37ca05abd9f556e4","17:17-f2d707dd60cbbe95","744:main-app-e2b4ac6faab5ed41"],"async":false}},"/Users/byronwade/Desktop/emailmework.com/app/globals.css":{"default":{"id":"9617","name":"default","chunks":["static/css/2b2c5c4a8fea1859.css"]}}}